snotify/__init__.py
snotify/core.py
snotify/channels/__init__.py
snotify/channels/base.py
snotify/channels/email.py
snotify/channels/telegram.py
snotify/channels/webhook.py
tests/__init__.py
tests/test_core.py
tests/test_email.py
tests/test_telegram.py
tests/test_webhook.py
snotify-0.2.2.dist-info/LICENSE
snotify-0.2.2.dist-info/METADATA
snotify-0.2.2.dist-info/WHEEL
snotify-0.2.2.dist-info/top_level.txt
snotify-0.2.2.dist-info/RECORD
