Metadata-Version: 2.1
Name: snotify
Version: 0.2.2
Summary: Lightweight notification manager for Telegram, Webhook, Email and Custom channels
Home-page: https://github.com/swtormy/snotify
Author: Konstantin Vasilev
Author-email: swtormy@yahoo.com
License: MIT
Project-URL: Documentation, https://github.com/swtormy/snotify#readme
Project-URL: Source, https://github.com/swtormy/snotify
Project-URL: Tracker, https://github.com/swtormy/snotify/issues
Keywords: notifications telegram,webhook,email
Classifier: Programming Language :: Python :: 3
Classifier: License :: OSI Approved :: MIT License
Classifier: Operating System :: OS Independent
Requires-Python: >=3.7
License-File: LICENSE
Requires-Dist: aiohttp>=3.11.6
Requires-Dist: aiosmtplib>=3.0.2
